{
  "created_at": "2024-03-22T01:52:11.943004+00:00",
  "elapsed": 0.252077,
  "encoding": "utf-8",
  "headers": {
    "Cache-Control": "private, no-store",
    "Connection": "keep-alive",
    "Content-Length": "4949",
    "Content-Type": "application/json",
    "Date": "Fri, 22 Mar 2024 01:52:11 GMT",
    "Strict-Transport-Security": "max-age=31536000",
    "Vary": "Origin",
    "X-Content-Type-Options": "nosniff",
    "X-Frame-Options": "Deny",
    "X-XSS-Protection": "1;mode=block"
  },
  "reason": "",
  "request": {
    "body": "",
    "cookies": {
      "TS0193e6a1": "01283c52a416a26a651463e2d91a85c30bfc1b99c028003c390cbb016ebd7a7858c1d4c9991b2adbc679b63e012300d859e2347dd0"
    },
    "headers": {
      "Accept": "*/*",
      "Accept-Encoding": "gzip, deflate",
      "Connection": "keep-alive",
      "Cookie": "TS0193e6a1=01283c52a416a26a651463e2d91a85c30bfc1b99c028003c390cbb016ebd7a7858c1d4c9991b2adbc679b63e012300d859e2347dd0",
      "User-Agent": "python-requests/2.31.0"
    },
    "method": "GET",
    "url": "https://geocoding.geo.census.gov/geocoder/geographies/coordinates?benchmark=Public_AR_Census2020&format=json&vintage=Census2020_Census2020&x=-73.755405&y=40.603995"
  },
  "status_code": 200,
  "url": "https://geocoding.geo.census.gov/geocoder/geographies/coordinates?benchmark=Public_AR_Census2020&format=json&vintage=Census2020_Census2020&x=-73.755405&y=40.603995",
  "_decoded_content": {
    "result": {
      "geographies": {
        "State Legislative Districts - Upper": [
          {
            "POP100": 346498,
            "GEOID": "36010",
            "CENTLAT": "+40.6457290",
            "AREAWATER": 14180281,
            "STATE": "36",
            "BASENAME": "10",
            "OID": "212904690195376",
            "LSADC": "LU",
            "SLDU": "010",
            "FUNCSTAT": "N",
            "INTPTLAT": "+40.6461179",
            "NAME": "State Senate District 10",
            "OBJECTID": 909,
            "CENTLON": "-073.7893472",
            "LSY": "2018",
            "HU100": 112841,
            "AREALAND": 57079145,
            "INTPTLON": "-073.7888580",
            "MTFCC": "G5210",
            "LDTYP": "O"
          }
        ],
        "States": [
          {
            "STATENS": "01779796",
            "POP100": 20201249,
            "GEOID": "36",
            "CENTLAT": "+42.9196161",
            "AREAWATER": 19256750161,
            "STATE": "36",
            "BASENAME": "New York",
            "STUSAB": "NY",
            "OID": "27490100833860",
            "LSADC": "00",
            "FUNCSTAT": "A",
            "INTPTLAT": "+42.9133974",
            "DIVISION": "2",
            "NAME": "New York",
            "REGION": "1",
            "OBJECTID": 51,
            "CENTLON": "-075.5941471",
            "AREALAND": 122049520861,
            "INTPTLON": "-075.5962723",
            "HU100": 8488066,
            "MTFCC": "G4000",
            "UR": "M"
          }
        ],
        "Combined Statistical Areas": [
          {
            "POP100": 23582649,
            "GEOID": "408",
            "CENTLAT": "+41.0667541",
            "AREAWATER": 8099265995,
            "BASENAME": "New York-Newark, NY-NJ-CT-PA",
            "OID": "2619013782255195",
            "LSADC": "M0",
            "FUNCSTAT": "S",
            "INTPTLAT": "+40.7749300",
            "NAME": "New York-Newark, NY-NJ-CT-PA CSA",
            "CSA": "408",
            "OBJECTID": 140,
            "CENTLON": "-073.8753122",
            "HU100": 9401953,
            "AREALAND": 32113500421,
            "INTPTLON": "-073.8737580",
            "MTFCC": "G3100"
          }
        ],
        "2020 Urban Areas - Corrected": [
          {
            "GEOID": "63217",
            "CENTLAT": "+40.7122656",
            "AREAWATER": 548707462,
            "BASENAME": "New York--Jersey City--Newark, NY--NJ",
            "OID": "27021287355931",
            "UA": "63217",
            "LSADC": "67",
            "FUNCSTAT": "S",
            "INTPTLAT": "+40.7121519",
            "NAME": "New York--Jersey City--Newark, NY--NJ Urban Area",
            "OBJECTID": 331,
            "CENTLON": "-073.9494543",
            "AREALAND": 8412591091,
            "INTPTLON": "-073.9501839",
            "MTFCC": "G3500"
          }
        ],
        "County Subdivisions": [
          {
            "COUSUB": "60323",
            "POP100": 2405464,
            "GEOID": "3608160323",
            "CENTLAT": "+40.6545736",
            "AREAWATER": 188444349,
            "STATE": "36",
            "BASENAME": "Queens",
            "OID": "27690307885935",
            "LSADC": "21",
            "FUNCSTAT": "G",
            "INTPTLAT": "+40.6546581",
            "NAME": "Queens borough",
            "OBJECTID": 18913,
            "CENTLON": "-073.8408699",
            "COUSUBCC": "Z1",
            "HU100": 896333,
            "AREALAND": 281594050,
            "INTPTLON": "-073.8412089",
            "MTFCC": "G4040",
            "COUSUBNS": "00979404",
            "UR": "M",
            "COUNTY": "081"
          }
        ],
        "State Legislative Districts - Lower": [
          {
            "POP100": 134567,
            "GEOID": "36031",
            "CENTLAT": "+40.6382913",
            "SLDL": "031",
            "AREAWATER": 13237199,
            "STATE": "36",
            "BASENAME": "31",
            "OID": "213904690195616",
            "LSADC": "L3",
            "FUNCSTAT": "N",
            "INTPTLAT": "+40.6307208",
            "NAME": "Assembly District 31",
            "OBJECTID": 2734,
            "CENTLON": "-073.7887100",
            "LSY": "2018",
            "HU100": 42497,
            "AREALAND": 38728556,
            "INTPTLON": "-073.7684928",
            "MTFCC": "G5220",
            "LDTYP": "O"
          }
        ],
        "Incorporated Places": [
          {
            "NECTAPCI": "N",
            "POP100": 8804190,
            "GEOID": "3651000",
            "CENTLAT": "+40.6624937",
            "AREAWATER": 445421632,
            "STATE": "36",
            "BASENAME": "New York",
            "OID": "27890287325779",
            "LSADC": "25",
            "PLACE": "51000",
            "FUNCSTAT": "A",
            "INTPTLAT": "+40.6627117",
            "NAME": "New York city",
            "OBJECTID": 614,
            "PLACECC": "C1",
            "CENTLON": "-073.9389043",
            "CBSAPCI": "Y",
            "HU100": 3618635,
            "AREALAND": 778165283,
            "INTPTLON": "-073.9386769",
            "PLACENS": "02395220",
            "MTFCC": "G4110",
            "UR": "M"
          }
        ],
        "Counties": [
          {
            "POP100": 2405464,
            "GEOID": "36081",
            "CENTLAT": "+40.6545736",
            "AREAWATER": 188444349,
            "STATE": "36",
            "BASENAME": "Queens",
            "OID": "27590307869814",
            "LSADC": "06",
            "FUNCSTAT": "C",
            "INTPTLAT": "+40.6546581",
            "NAME": "Queens County",
            "OBJECTID": 1560,
            "CENTLON": "-073.8408699",
            "COUNTYCC": "H6",
            "COUNTYNS": "00974139",
            "AREALAND": 281594050,
            "INTPTLON": "-073.8412089",
            "HU100": 896333,
            "MTFCC": "G4020",
            "UR": "M",
            "COUNTY": "081"
          }
        ],
        "116th Congressional Districts": [
          {
            "POP100": 778780,
            "GEOID": "3605",
            "CENTLAT": "+40.5965309",
            "CDSESSN": "116",
            "AREAWATER": 193585603,
            "STATE": "36",
            "BASENAME": "5",
            "OID": "211904690193512",
            "LSADC": "C2",
            "FUNCSTAT": "N",
            "INTPTLAT": "+40.5965625",
            "NAME": "Congressional District 5",
            "OBJECTID": 385,
            "CENTLON": "-073.8263892",
            "HU100": 256319,
            "AREALAND": 134489222,
            "INTPTLON": "-073.8272118",
            "CD116": "05",
            "MTFCC": "G5200"
          }
        ],
        "Census Tracts": [
          {
            "POP100": 4817,
            "GEOID": "36081100803",
            "CENTLAT": "+40.6031480",
            "AREAWATER": 0,
            "STATE": "36",
            "BASENAME": "1008.03",
            "OID": "2079015682491985",
            "LSADC": "CT",
            "FUNCSTAT": "S",
            "INTPTLAT": "+40.6031480",
            "NAME": "Census Tract 1008.03",
            "OBJECTID": 7844,
            "TRACT": "100803",
            "CENTLON": "-073.7575401",
            "HU100": 1451,
            "AREALAND": 347303,
            "INTPTLON": "-073.7575401",
            "MTFCC": "G5020",
            "UR": "U",
            "COUNTY": "081"
          }
        ],
        "Census Blocks": [
          {
            "SUFFIX": "",
            "POP100": 274,
            "GEOID": "360811008031000",
            "CENTLAT": "+40.6038204",
            "BLOCK": "1000",
            "AREAWATER": 0,
            "STATE": "36",
            "BASENAME": "1000",
            "OID": "210701006106576",
            "LSADC": "BK",
            "INTPTLAT": "+40.6038204",
            "FUNCSTAT": "S",
            "NAME": "Block 1000",
            "OBJECTID": 1391839,
            "TRACT": "100803",
            "CENTLON": "-073.7557552",
            "BLKGRP": "1",
            "AREALAND": 32886,
            "HU100": 119,
            "INTPTLON": "-073.7557552",
            "MTFCC": "G5040",
            "LWBLKTYP": "L",
            "UR": "U",
            "COUNTY": "081"
          }
        ]
      },
      "input": {
        "vintage": {
          "isDefault": true,
          "id": "2020",
          "vintageName": "Census2020_Census2020",
          "vintageDescription": "Census 2020 Vintage - Census 2020 Benchmark"
        },
        "location": {
          "x": -73.755405,
          "y": 40.603995
        },
        "benchmark": {
          "isDefault": false,
          "benchmarkDescription": "Public Address Ranges - Census 2020 Benchmark",
          "id": "2020",
          "benchmarkName": "Public_AR_Census2020"
        }
      }
    }
  }
}